sm_2/__init__.py
sm_2/sm_2.py
sm_2-0.3.0.dist-info/LICENSE
sm_2-0.3.0.dist-info/METADATA
sm_2-0.3.0.dist-info/WHEEL
sm_2-0.3.0.dist-info/top_level.txt
sm_2-0.3.0.dist-info/RECORD
