Metadata-Version: 2.1
Name: sm-2
Version: 0.3.0
Summary: SM-2 spaced repetition scheduler
Author-email: Joshua Hamilton <hamiltonjoshuadavid@gmail.com>
License: MIT License
Project-URL: homepage, https://github.com/open-spaced-repetition/sm-2
Keywords: sm-2,spaced-repetition,flashcard
Classifier: Programming Language :: Python :: 3
Classifier: License :: OSI Approved :: MIT License
Classifier: Operating System :: OS Independent
Requires-Python: >=3.10
License-File: LICENSE
